pycur/__init__.py
pycur-2023.7.31.1.dist-info/METADATA
pycur-2023.7.31.1.dist-info/WHEEL
pycur-2023.7.31.1.dist-info/top_level.txt
pycur-2023.7.31.1.dist-info/RECORD
