Metadata-Version: 2.1
Name: pycur
Version: 2023.7.31.1
Summary: Modifying cursors is now easier than ever!
Home-page: https://pycur.glitch.me/
Author: RixTheTyrunt
Author-email: rixthetyrunt@gmail.com
License: UNKNOWN
Platform: UNKNOWN
Requires-Python: >=3
